{"type": "FeatureCollection", "crs": {"type": "name", "properties": {"name": "urn:ogc:def:crs:OGC:1.3:CRS84"}}, "features": [{"type": "Feature", "geometry": {"type": "Point", "coordinates": [139.63055, 35.52758]}, "properties": {"Shanai": "", "Name": "大曽根保育園", "Full": "76", "Foundation": "20150401", "VacancyDate": "", "Holiday": "", "Ownership": "", "Y": "35.52758", "Kodomo": "", "HID": "1", "Close": "19：00", "Owner": "", "Type": "公立認可保育所", "url": "http://www.city.yokohama.lg.jp/kohoku/hoikuen/osone/", "Add2": "", "Label": "大曽根保育園", "Vacancy": "", "FAX": "045-531-0125", "H24": "", "Memo": "", "TEL": "045-531-0034", "Night": "", "Pre": "Y", "Bus": "N", "Lunch": "2", "Extra": "", "Extra_type": "", "Proof": "", "Temp": "Y", "Add1": "横浜市港北区大曽根2-5-1", "Open": "7：00", "X": "139.63055", "AgeE": "就学前", "AgeS": "１歳"}}, {"type": "Feature", "geometry": {"type": "Point", "coordinates": [139.637714, 35.505925]}, "properties": {"Shanai": "", "Name": "菊名保育園", "Full": "78", "Foundation": "", "VacancyDate": "", "Holiday": "", "Ownership": "", "Y": "35.505925", "Kodomo": "", "HID": "2", "Close": "19：00", "Owner": "", "Type": "公立認可保育所", "url": "http://www.city.yokohama.lg.jp/kohoku/hoikuen/kikuna/", "Add2": "", "Label": "菊名保育園", "Vacancy": "", "FAX": "045-433-1261", "H24": "", "Memo": "", "TEL": "045-433-1259", "Night": "", "Pre": "N", "Bus": "Y", "Lunch": "", "Extra": "", "Extra_type": "", "Proof": "", "Temp": "Y", "Add1": "横浜市港北区菊名3-10-20", "Open": "7：00", "X": "139.637714", "AgeE": "就学前", "AgeS": "１歳"}}]}